<?xml version="1.0" encoding="utf-8"?>
<ArrayOfQuizQuestion xmlns:xsi="http://www.w3.org/2001/XMLSchema-instance" xmlns:xsd="http://www.w3.org/2001/XMLSchema">
  <QuizQuestion>
    <question>What is your name?</question>
    <questionOption>
      <string>(A) Dele</string>
      <string>(B) Wale</string>
      <string>(C) Wunmu</string>
      <string>(D) Olayode</string>
      <string>(E) Maryam</string>
    </questionOption>
    <correctOption>(E) Maryam</correctOption>
  </QuizQuestion>
</ArrayOfQuizQuestion>